argopt/__init__.py
argopt/_argopt.py
argopt/_dist_ver.py
argopt/_docopt.py
argopt/_utils.py
argopt-0.9.1.dist-info/licenses/LICENCE
argopt-0.9.1.dist-info/METADATA
argopt-0.9.1.dist-info/WHEEL
argopt-0.9.1.dist-info/top_level.txt
argopt-0.9.1.dist-info/RECORD
